LICENSE
README.md
setup.py
xarray_symTensor2d/__init__.py
xarray_symTensor2d/xarray_symTensor2d.py
xarray_symTensor2d.egg-info/PKG-INFO
xarray_symTensor2d.egg-info/SOURCES.txt
xarray_symTensor2d.egg-info/dependency_links.txt
xarray_symTensor2d.egg-info/top_level.txt