Metadata-Version: 2.1
Name: xarray_symTensor2d
Version: 0.1
Summary: Tools to work on mpa of 2d symmetric tensor
Home-page: https://github.com/ThomasChauve/xarray_symTensor2d
Author: Thomas Chauve
Author-email: thomas.chauve@univ-grenoble-alpes.fr
License: GPL-3.0
Classifier: Intended Audience :: Science/Research
Classifier: License :: OSI Approved :: GNU General Public License v3 (GPLv3)
Classifier: Operating System :: OS Independent
Classifier: Programming Language :: Python :: 3 :: Only
Requires-Python: >=3.7
License-File: LICENSE
